pyyoutube/__init__.py
pyyoutube/__version__.py
pyyoutube/api.py
pyyoutube/error.py
pyyoutube/models/__init__.py
pyyoutube/models/activity.py
pyyoutube/models/auth.py
pyyoutube/models/base.py
pyyoutube/models/caption.py
pyyoutube/models/category.py
pyyoutube/models/channel.py
pyyoutube/models/channel_section.py
pyyoutube/models/comment.py
pyyoutube/models/common.py
pyyoutube/models/i18n.py
pyyoutube/models/member.py
pyyoutube/models/memberships_level.py
pyyoutube/models/mixins.py
pyyoutube/models/playlist.py
pyyoutube/models/playlist_item.py
pyyoutube/models/search_result.py
pyyoutube/models/subscription.py
pyyoutube/models/video.py
pyyoutube/models/video_abuse_report_reason.py
pyyoutube/utils/__init__.py
pyyoutube/utils/constants.py
pyyoutube/utils/params_checker.py
pyyoutube/youtube_utils.py
python_youtube_async-1.0.0.dist-info/LICENSE
python_youtube_async-1.0.0.dist-info/WHEEL
python_youtube_async-1.0.0.dist-info/METADATA
python_youtube_async-1.0.0.dist-info/RECORD
