Metadata-Version: 2.1
Name: python-youtube-async
Version: 1.0.0
Summary: A Python wrapper around for YouTube Data API.
Home-page: https://github.com/niwla23/python-youtube-async
License: MIT
Keywords: youtube-api,youtube-v3-api,youtube-data-api,youtube-sdk,async
Author: ikaroskun
Author-email: merle.liukun@gmail.com
Requires-Python: >=3.6,<4.0
Classifier: Intended Audience :: Developers
Classifier: License :: OSI Approved :: Apache Software License
Classifier: License :: OSI Approved :: MIT License
Classifier: Programming Language :: Python
Classifier: Programming Language :: Python :: 3
Classifier: Programming Language :: Python :: 3.10
Classifier: Programming Language :: Python :: 3.6
Classifier: Programming Language :: Python :: 3.7
Classifier: Programming Language :: Python :: 3.8
Classifier: Programming Language :: Python :: 3.9
Classifier: Programming Language :: Python :: Implementation :: CPython
Classifier: Programming Language :: Python :: Implementation :: PyPy
Classifier: Topic :: Software Development :: Libraries :: Python Modules
Requires-Dist: aiohttp (>=3.8.0,<4.0.0)
Requires-Dist: dataclasses-json (>=0.5.3,<0.6.0)
Requires-Dist: isodate (>=0.6.0,<0.7.0)
Requires-Dist: requests (>=2.24.0,<3.0.0)
Requires-Dist: requests-oauthlib (>=1.3.0,<2.0.0)
Project-URL: Repository, https://github.com/niwla23/python-youtube-async
